[
  {
    "current_week_rank": "1",
    "previous_week_rank": "(1)",
    "movie": "Tootsie",
    "distributor": "Sony Pictures",
    "gross": "$15,188,656",
    "change": "-16%",
    "num_theaters": "1,115",
    "per_theater": "$13,622",
    "total_gross": "$59,790,317",
    "days": "4"
  },
  {
    "current_week_rank": "2",
    "previous_week_rank": "(5)",
    "movie": "48 Hrs.",
    "distributor": "Paramount Pictures",
    "gross": "$6,570,579",
    "change": "-17%",
    "num_theaters": "920",
    "per_theater": "$7,142",
    "total_gross": "$32,675,154",
    "days": "6"
  },
  {
    "current_week_rank": "3",
    "previous_week_rank": "(3)",
    "movie": "The Verdict",
    "distributor": "20th Century Fox",
    "gross": "$5,907,031",
    "change": "-20%",
    "num_theaters": "658",
    "per_theater": "$8,977",
    "total_gross": "$24,323,030",
    "days": "6"
  },
  {
    "current_week_rank": "4",
    "previous_week_rank": "(2)",
    "movie": "The Dark Crystal",
    "distributor": "Universal",
    "gross": "$5,563,940",
    "change": "-40%",
    "num_theaters": "1,043",
    "per_theater": "$5,335",
    "total_gross": "$29,120,000",
    "days": "4"
  },
  {
    "current_week_rank": "5",
    "previous_week_rank": "(6)",
    "movie": "The Toy",
    "distributor": "Sony Pictures",
    "gross": "$4,848,822",
    "change": "-47%",
    "num_theaters": "1,459",
    "per_theater": "$3,323",
    "total_gross": "$36,040,507",
    "days": "5"
  },
  {
    "current_week_rank": "6",
    "previous_week_rank": "(4)",
    "movie": "Best Friends",
    "distributor": "Warner Bros.",
    "gross": "$4,643,479",
    "change": "-45%",
    "num_theaters": "1,069",
    "per_theater": "$4,344",
    "total_gross": "$25,936,613",
    "days": "4"
  },
  {
    "current_week_rank": "7",
    "previous_week_rank": "(7)",
    "movie": "ET: The Extra-Terrestrial",
    "distributor": "Universal",
    "gross": "$3,527,000",
    "change": "-52%",
    "num_theaters": "842",
    "per_theater": "$4,189",
    "total_gross": "$326,973,000",
    "days": "31"
  },
  {
    "current_week_rank": "8",
    "previous_week_rank": "(8)",
    "movie": "Kiss Me Goodbye",
    "distributor": "20th Century Fox",
    "gross": "$2,815,243",
    "change": "-22%",
    "num_theaters": "787",
    "per_theater": "$3,577",
    "total_gross": "$10,609,571",
    "days": "4"
  },
  {
    "current_week_rank": "9",
    "previous_week_rank": "(9)",
    "movie": "Airplane II: The Sequel",
    "distributor": "Paramount Pictures",
    "gross": "$1,974,673",
    "change": "-67%",
    "num_theaters": "925",
    "per_theater": "$2,135",
    "total_gross": "$23,046,849",
    "days": "5"
  },
  {
    "current_week_rank": "10",
    "previous_week_rank": "(11)",
    "movie": "An Officer and a Gentleman",
    "distributor": "Paramount Pictures",
    "gross": "$1,835,681",
    "change": "-12%",
    "num_theaters": "590",
    "per_theater": "$3,111",
    "total_gross": "$111,874,551",
    "days": "25"
  },
  {
    "current_week_rank": "11",
    "previous_week_rank": "(10)",
    "movie": "Peter Pan",
    "distributor": "RKO Radio Pictures",
    "gross": "$1,773,660",
    "change": "-63%",
    "num_theaters": "656",
    "per_theater": "$2,704",
    "total_gross": "$11,699,591",
    "days": "1,563"
  },
  {
    "current_week_rank": "12",
    "previous_week_rank": "(13)",
    "movie": "Six Weeks",
    "distributor": "Universal",
    "gross": "$1,083,000",
    "change": "-51%",
    "num_theaters": "549",
    "per_theater": "$1,973",
    "total_gross": "$6,256,000",
    "days": "4"
  },
  {
    "current_week_rank": "13",
    "previous_week_rank": "(14)",
    "movie": "First Blood",
    "distributor": "Orion Pictures",
    "gross": "$1,028,923",
    "change": "+28%",
    "num_theaters": "511",
    "per_theater": "$2,014",
    "total_gross": "$44,581,112",
    "days": "12"
  },
  {
    "current_week_rank": "14",
    "previous_week_rank": "(16)",
    "movie": "Gandhi",
    "distributor": "Sony Pictures",
    "gross": "$432,510",
    "change": "-9%",
    "num_theaters": "12",
    "per_theater": "$36,043",
    "total_gross": "$1,956,885",
    "days": "6"
  },
  {
    "current_week_rank": "15",
    "previous_week_rank": "(17)",
    "movie": "Sophie's Choice",
    "distributor": "Universal",
    "gross": "$352,949",
    "change": "-17%",
    "num_theaters": "10",
    "per_theater": "$35,295",
    "total_gross": "$1,839,666",
    "days": "5"
  },
  {
    "current_week_rank": "16",
    "previous_week_rank": "(18)",
    "movie": "The Man From Snowy River",
    "distributor": "20th Century Fox",
    "gross": "$297,310",
    "change": "-47%",
    "num_theaters": "97",
    "per_theater": "$3,065",
    "total_gross": "$6,967,269",
    "days": "11"
  }
]