[
  {
    "current_week_rank": "1",
    "previous_week_rank": "(-)",
    "movie": "Terms of Endearment",
    "distributor": "Paramount Pictures",
    "gross": "$8,369,007",
    "change": "",
    "num_theaters": "1,027",
    "per_theater": "$8,149",
    "total_gross": "$50,570,312",
    "days": "8"
  },
  {
    "current_week_rank": "2",
    "previous_week_rank": "(-)",
    "movie": "Sudden Impact",
    "distributor": "Warner Bros.",
    "gross": "$6,890,838",
    "change": "",
    "num_theaters": "1,582",
    "per_theater": "$4,356",
    "total_gross": "$50,593,409",
    "days": "5"
  },
  {
    "current_week_rank": "3",
    "previous_week_rank": "(-)",
    "movie": "Scarface",
    "distributor": "Universal",
    "gross": "$4,134,000",
    "change": "",
    "num_theaters": "885",
    "per_theater": "$4,671",
    "total_gross": "$27,355,000",
    "days": "5"
  },
  {
    "current_week_rank": "4",
    "previous_week_rank": "(-)",
    "movie": "Yentl",
    "distributor": "MGM/UA Classics",
    "gross": "$3,675,247",
    "change": "",
    "num_theaters": "609",
    "per_theater": "$6,035",
    "total_gross": "$23,365,580",
    "days": "8"
  },
  {
    "current_week_rank": "5",
    "previous_week_rank": "(-)",
    "movie": "Uncommon Valor",
    "distributor": "Paramount Pictures",
    "gross": "$3,647,789",
    "change": "",
    "num_theaters": "1,076",
    "per_theater": "$3,390",
    "total_gross": "$18,542,008",
    "days": "4"
  },
  {
    "current_week_rank": "6",
    "previous_week_rank": "(-)",
    "movie": "Silkwood",
    "distributor": "20th Century Fox",
    "gross": "$2,875,884",
    "change": "",
    "num_theaters": "287",
    "per_theater": "$10,021",
    "total_gross": "$11,584,158",
    "days": "5"
  },
  {
    "current_week_rank": "7",
    "previous_week_rank": "(-)",
    "movie": "Two of a Kind",
    "distributor": "20th Century Fox",
    "gross": "$2,869,999",
    "change": "",
    "num_theaters": "1,136",
    "per_theater": "$2,526",
    "total_gross": "$18,277,949",
    "days": "4"
  },
  {
    "current_week_rank": "8",
    "previous_week_rank": "(-)",
    "movie": "Christine",
    "distributor": "Sony Pictures",
    "gross": "$2,533,471",
    "change": "",
    "num_theaters": "1,039",
    "per_theater": "$2,438",
    "total_gross": "$16,372,552",
    "days": "5"
  },
  {
    "current_week_rank": "9",
    "previous_week_rank": "(-)",
    "movie": "The Big Chill",
    "distributor": "Sony Pictures",
    "gross": "$2,229,820",
    "change": "",
    "num_theaters": "710",
    "per_theater": "$3,141",
    "total_gross": "$46,145,228",
    "days": "16"
  },
  {
    "current_week_rank": "10",
    "previous_week_rank": "(-)",
    "movie": "Gorky Park",
    "distributor": "Orion Pictures",
    "gross": "$2,180,822",
    "change": "",
    "num_theaters": "571",
    "per_theater": "$3,819",
    "total_gross": "$9,783,425",
    "days": "4"
  },
  {
    "current_week_rank": "11",
    "previous_week_rank": "(-)",
    "movie": "D.C. Cab",
    "distributor": "Universal",
    "gross": "$2,015,000",
    "change": "",
    "num_theaters": "815",
    "per_theater": "$2,472",
    "total_gross": "$10,238,000",
    "days": "4"
  },
  {
    "current_week_rank": "12",
    "previous_week_rank": "(-)",
    "movie": "The Man Who Loved Women",
    "distributor": "Sony Pictures",
    "gross": "$1,911,372",
    "change": "",
    "num_theaters": "809",
    "per_theater": "$2,363",
    "total_gross": "$8,867,536",
    "days": "4"
  },
  {
    "current_week_rank": "13",
    "previous_week_rank": "(-)",
    "movie": "To Be or Not to Be",
    "distributor": "20th Century Fox",
    "gross": "$1,818,501",
    "change": "",
    "num_theaters": "593",
    "per_theater": "$3,067",
    "total_gross": "$9,277,203",
    "days": "4"
  },
  {
    "current_week_rank": "14",
    "previous_week_rank": "(-)",
    "movie": "The Rescuers",
    "distributor": "Walt Disney",
    "gross": "$1,363,116",
    "change": "",
    "num_theaters": "858",
    "per_theater": "$1,589",
    "total_gross": "$14,800,512",
    "days": "343"
  },
  {
    "current_week_rank": "15",
    "previous_week_rank": "(-)",
    "movie": "Star Wars Ep. VI: Return of\u2026",
    "distributor": "20th Century Fox",
    "gross": "$966,005",
    "change": "",
    "num_theaters": "540",
    "per_theater": "$1,789",
    "total_gross": "$250,574,773",
    "days": "34"
  },
  {
    "current_week_rank": "16",
    "previous_week_rank": "(-)",
    "movie": "Never Say Never Again",
    "distributor": "Warner Bros.",
    "gross": "$630,456",
    "change": "",
    "num_theaters": "403",
    "per_theater": "$1,564",
    "total_gross": "$54,198,733",
    "days": "14"
  },
  {
    "current_week_rank": "17",
    "previous_week_rank": "(-)",
    "movie": "Educating Rita",
    "distributor": "Sony Pictures",
    "gross": "$542,391",
    "change": "",
    "num_theaters": "207",
    "per_theater": "$2,620",
    "total_gross": "$10,786,857",
    "days": "17"
  },
  {
    "current_week_rank": "18",
    "previous_week_rank": "(-)",
    "movie": "The Right Stuff",
    "distributor": "Warner Bros.",
    "gross": "$521,522",
    "change": "",
    "num_theaters": "99",
    "per_theater": "$5,268",
    "total_gross": "$14,031,907",
    "days": "12"
  },
  {
    "current_week_rank": "19",
    "previous_week_rank": "(-)",
    "movie": "Never Cry Wolf",
    "distributor": "Walt Disney",
    "gross": "$403,236",
    "change": "",
    "num_theaters": "47",
    "per_theater": "$8,579",
    "total_gross": "$7,934,828",
    "days": "14"
  },
  {
    "current_week_rank": "20",
    "previous_week_rank": "(-)",
    "movie": "Experience Preferred",
    "distributor": "Samuel Goldwyn Films",
    "gross": "$104,848",
    "change": "",
    "num_theaters": "17",
    "per_theater": "$6,168",
    "total_gross": "$595,271",
    "days": "10"
  },
  {
    "current_week_rank": "21",
    "previous_week_rank": "(-)",
    "movie": "Star 80",
    "distributor": "Warner Bros.",
    "gross": "$100,328",
    "change": "",
    "num_theaters": "12",
    "per_theater": "$8,361",
    "total_gross": "$1,569,492",
    "days": "10"
  },
  {
    "current_week_rank": "22",
    "previous_week_rank": "(-)",
    "movie": "The Dresser",
    "distributor": "Sony Pictures",
    "gross": "$67,639",
    "change": "",
    "num_theaters": "3",
    "per_theater": "$22,546",
    "total_gross": "$349,747",
    "days": "6"
  }
]