[
  {
    "current_week_rank": "1",
    "previous_week_rank": "(-)",
    "movie": "Platoon",
    "distributor": "Orion Pictures",
    "gross": "$15,759,082",
    "change": "",
    "num_theaters": "1,194",
    "per_theater": "$13,199",
    "total_gross": "$57,657,764",
    "days": "9"
  },
  {
    "current_week_rank": "2",
    "previous_week_rank": "(-)",
    "movie": "Outrageous Fortune",
    "distributor": "Walt Disney",
    "gross": "$7,535,380",
    "change": "",
    "num_theaters": "1,302",
    "per_theater": "$5,788",
    "total_gross": "$22,773,451",
    "days": "3"
  },
  {
    "current_week_rank": "3",
    "previous_week_rank": "new",
    "movie": "Mannequin",
    "distributor": "20th Century Fox",
    "gross": "$7,064,981",
    "change": "",
    "num_theaters": "992",
    "per_theater": "$7,122",
    "total_gross": "$7,064,981",
    "days": "1"
  },
  {
    "current_week_rank": "4",
    "previous_week_rank": "new",
    "movie": "Over the Top",
    "distributor": "Warner Bros.",
    "gross": "$6,164,741",
    "change": "",
    "num_theaters": "1,758",
    "per_theater": "$3,507",
    "total_gross": "$6,164,741",
    "days": "1"
  },
  {
    "current_week_rank": "5",
    "previous_week_rank": "(-)",
    "movie": "Black Widow",
    "distributor": "20th Century Fox",
    "gross": "$4,933,031",
    "change": "",
    "num_theaters": "736",
    "per_theater": "$6,702",
    "total_gross": "$9,467,288",
    "days": "2"
  },
  {
    "current_week_rank": "6",
    "previous_week_rank": "(-)",
    "movie": "Crocodile Dundee",
    "distributor": "Paramount Pictures",
    "gross": "$3,291,332",
    "change": "",
    "num_theaters": "1,200",
    "per_theater": "$2,743",
    "total_gross": "$147,247,417",
    "days": "21"
  },
  {
    "current_week_rank": "7",
    "previous_week_rank": "(-)",
    "movie": "From the Hip",
    "distributor": "De Laurentiis Enter\u2026",
    "gross": "$2,663,478",
    "change": "",
    "num_theaters": "971",
    "per_theater": "$2,743",
    "total_gross": "$5,719,646",
    "days": "2"
  },
  {
    "current_week_rank": "8",
    "previous_week_rank": "(-)",
    "movie": "Light of Day",
    "distributor": "Sony Pictures",
    "gross": "$2,425,006",
    "change": "",
    "num_theaters": "1,040",
    "per_theater": "$2,332",
    "total_gross": "$6,673,316",
    "days": "2"
  },
  {
    "current_week_rank": "9",
    "previous_week_rank": "(-)",
    "movie": "Star Trek IV: The Voyage Home",
    "distributor": "Paramount Pictures",
    "gross": "$1,648,874",
    "change": "",
    "num_theaters": "717",
    "per_theater": "$2,300",
    "total_gross": "$103,782,909",
    "days": "13"
  },
  {
    "current_week_rank": "10",
    "previous_week_rank": "(-)",
    "movie": "Radio Days",
    "distributor": "Orion Pictures",
    "gross": "$1,616,562",
    "change": "",
    "num_theaters": "140",
    "per_theater": "$11,547",
    "total_gross": "$5,428,116",
    "days": "3"
  }
]